{
  "type": "FeatureCollection",
  "metadata": {
    "generated": 1768298127000,
    "url": "https://earthquake.usgs.gov/earthquakes/feed/v1.0/summary/all_day.geojson",
    "title": "USGS All Earthquakes, Past Day",
    "status": 200,
    "api": "1.14.1",
    "count": 226
  },
  "features": [
    {
      "type": "Feature",
      "properties": {
        "mag": 3.05,
        "place": "9 km SSE of Maria Antonia, Puerto Rico",
        "time": 1768286513840,
        "updated": 1768289483470,
        "tz": null,
        "url": "https://earthquake.usgs.gov/earthquakes/eventpage/pr71505018",
        "detail": "https://earthquake.usgs.gov/earthquakes/feed/v1.0/detail/pr71505018.geojson",
        "felt": null,
        "cdi": null,
        "mmi": null,
        "alert": null,
        "status": "reviewed",
        "tsunami": 0,
        "sig": 143,
        "net": "pr",
        "code": "71505018",
        "ids": ",pr71505018,",
        "sources": ",pr,",
        "types": ",origin,phase-data,",
        "nst": 20,
        "dmin": 0.07441,
        "rms": 0.09,
        "gap": 206,
        "magType": "md",
        "type": "earthquake",
        "title": "M 3.1 - 9 km SSE of Maria Antonia, Puerto Rico"
      },
      "geometry": {
        "type": "Point",
        "coordinates": [
          -66.8438333333333,
          17.9013333333333,
          13.48
        ]
      },
      "id": "pr71505018"
    },
    {
      "type": "Feature",
      "properties": {
        "mag": 1.7,
        "place": "9 km SSE of Maria Antonia, Puerto Rico",
        "time": 1768285435720,
        "updated": 1768287648040,
        "tz": null,
        "url": "https://earthquake.usgs.gov/earthquakes/eventpage/pr71505013",
        "detail": "https://earthquake.usgs.gov/earthquakes/feed/v1.0/detail/pr71505013.geojson",
        "felt": null,
        "cdi": null,
        "mmi": null,
        "alert": null,
        "status": "reviewed",
        "tsunami": 0,
        "sig": 44,
        "net": "pr",
        "code": "71505013",
        "ids": ",pr71505013,",
        "sources": ",pr,",
        "types": ",origin,phase-data,",
        "nst": 7,
        "dmin": 0.06908,
        "rms": 0.12,
        "gap": 233,
        "magType": "md",
        "type": "earthquake",
        "title": "M 1.7 - 9 km SSE of Maria Antonia, Puerto Rico"
      },
      "geometry": {
        "type": "Point",
        "coordinates": [
          -66.8438333333333,
          17.907,
          15.26
        ]
      },
      "id": "pr71505013"
    },
    {
      "type": "Feature",
      "properties": {
        "mag": 2.13,
        "place": "9 km SSE of Maria Antonia, Puerto Rico",
        "time": 1768285355950,
        "updated": 1768287124640,
        "tz": null,
        "url": "https://earthquake.usgs.gov/earthquakes/eventpage/pr71505008",
        "detail": "https://earthquake.usgs.gov/earthquakes/feed/v1.0/detail/pr71505008.geojson",
        "felt": null,
        "cdi": null,
        "mmi": null,
        "alert": null,
        "status": "reviewed",
        "tsunami": 0,
        "sig": 70,
        "net": "pr",
        "code": "71505008",
        "ids": ",pr71505008,",
        "sources": ",pr,",
        "types": ",origin,phase-data,",
        "nst": 10,
        "dmin": 0.07595,
        "rms": 0.12,
        "gap": 234,
        "magType": "md",
        "type": "earthquake",
        "title": "M 2.1 - 9 km SSE of Maria Antonia, Puerto Rico"
      },
      "geometry": {
        "type": "Point",
        "coordinates": [
          -66.8456666666667,
          17.8991666666667,
          14.14
        ]
      },
      "id": "pr71505008"
    },
    {
      "type": "Feature",
      "properties": {
        "mag": 3.13,
        "place": "2 km NE of Bayamón, Puerto Rico",
        "time": 1768278939130,
        "updated": 1768280124610,
        "tz": null,
        "url": "https://earthquake.usgs.gov/earthquakes/eventpage/pr71504998",
        "detail": "https://earthquake.usgs.gov/earthquakes/feed/v1.0/detail/pr71504998.geojson",
        "felt": null,
        "cdi": null,
        "mmi": null,
        "alert": null,
        "status": "reviewed",
        "tsunami": 0,
        "sig": 151,
        "net": "pr",
        "code": "71504998",
        "ids": ",pr71504998,",
        "sources": ",pr,",
        "types": ",origin,phase-data,",
        "nst": 19,
        "dmin": 0.1196,
        "rms": 0.21,
        "gap": 169,
        "magType": "md",
        "type": "earthquake",
        "title": "M 3.1 - 2 km NE of Bayamón, Puerto Rico"
      },
      "geometry": {
        "type": "Point",
        "coordinates": [
          -66.1376666666667,
          18.4176666666667,
          119.44
        ]
      },
      "id": "pr71504998"
    },
    {
      "type": "Feature",
      "properties": {
        "mag": 3.36,
        "place": "133 km NNE of Vieques, Puerto Rico",
        "time": 1768250591250,
        "updated": 1768254545040,
        "tz": null,
        "url": "https://earthquake.usgs.gov/earthquakes/eventpage/pr71504988",
        "detail": "https://earthquake.usgs.gov/earthquakes/feed/v1.0/detail/pr71504988.geojson",
        "felt": null,
        "cdi": null,
        "mmi": null,
        "alert": null,
        "status": "reviewed",
        "tsunami": 0,
        "sig": 174,
        "net": "pr",
        "code": "71504988",
        "ids": ",us7000rp9g,pr71504988,",
        "sources": ",us,pr,",
        "types": ",origin,phase-data,",
        "nst": 13,
        "dmin": 1.271,
        "rms": 0.07,
        "gap": 270,
        "magType": "md",
        "type": "earthquake",
        "title": "M 3.4 - 133 km NNE of Vieques, Puerto Rico"
      },
      "geometry": {
        "type": "Point",
        "coordinates": [
          -65.3936666666667,
          19.561,
          11.08
        ]
      },
      "id": "pr71504988"
    }
  ],
  "bbox": [
    -179.9992,
    -59.9202,
    -1.96,
    177.659,
    64.97,
    566.522
  ]
}
