{
  "type": "FeatureCollection",
  "metadata": {
    "generated": 1752837225000,
    "url": "https://earthquake.usgs.gov/earthquakes/feed/v1.0/summary/all_day.geojson",
    "title": "USGS All Earthquakes, Past Day",
    "status": 200,
    "api": "1.14.1",
    "count": 246
  },
  "features": [
    {
      "type": "Feature",
      "properties": {
        "mag": 2.17,
        "place": "2 km NNE of Yauco, Puerto Rico",
        "time": 1752834836260,
        "updated": 1752835802190,
        "tz": null,
        "url": "https://earthquake.usgs.gov/earthquakes/eventpage/pr71489603",
        "detail": "https://earthquake.usgs.gov/earthquakes/feed/v1.0/detail/pr71489603.geojson",
        "felt": null,
        "cdi": null,
        "mmi": null,
        "alert": null,
        "status": "reviewed",
        "tsunami": 0,
        "sig": 72,
        "net": "pr",
        "code": "71489603",
        "ids": ",pr71489603,",
        "sources": ",pr,",
        "types": ",origin,phase-data,",
        "nst": 6,
        "dmin": 0.08431,
        "rms": 0.16,
        "gap": 146,
        "magType": "md",
        "type": "earthquake",
        "title": "M 2.2 - 2 km NNE of Yauco, Puerto Rico"
      },
      "geometry": {
        "type": "Point",
        "coordinates": [
          -66.8393333333333,
          18.0525,
          12.33
        ]
      },
      "id": "pr71489603"
    },
    {
      "type": "Feature",
      "properties": {
        "mag": 2.37,
        "place": "2 km S of Indios, Puerto Rico",
        "time": 1752834477790,
        "updated": 1752835079730,
        "tz": null,
        "url": "https://earthquake.usgs.gov/earthquakes/eventpage/pr71489593",
        "detail": "https://earthquake.usgs.gov/earthquakes/feed/v1.0/detail/pr71489593.geojson",
        "felt": null,
        "cdi": null,
        "mmi": null,
        "alert": null,
        "status": "reviewed",
        "tsunami": 0,
        "sig": 86,
        "net": "pr",
        "code": "71489593",
        "ids": ",pr71489593,",
        "sources": ",pr,",
        "types": ",origin,phase-data,",
        "nst": 7,
        "dmin": 0.04955,
        "rms": 0.16,
        "gap": 207,
        "magType": "md",
        "type": "earthquake",
        "title": "M 2.4 - 2 km S of Indios, Puerto Rico"
      },
      "geometry": {
        "type": "Point",
        "coordinates": [
          -66.8165,
          17.9675,
          17.64
        ]
      },
      "id": "pr71489593"
    },
    {
      "type": "Feature",
      "properties": {
        "mag": 2.13,
        "place": "1 km SE of Indios, Puerto Rico",
        "time": 1752831509810,
        "updated": 1752832155740,
        "tz": null,
        "url": "https://earthquake.usgs.gov/earthquakes/eventpage/pr71489583",
        "detail": "https://earthquake.usgs.gov/earthquakes/feed/v1.0/detail/pr71489583.geojson",
        "felt": null,
        "cdi": null,
        "mmi": null,
        "alert": null,
        "status": "reviewed",
        "tsunami": 0,
        "sig": 70,
        "net": "pr",
        "code": "71489583",
        "ids": ",pr71489583,",
        "sources": ",pr,",
        "types": ",origin,phase-data,",
        "nst": 6,
        "dmin": 0.06593,
        "rms": 0.06,
        "gap": 190,
        "magType": "md",
        "type": "earthquake",
        "title": "M 2.1 - 1 km SE of Indios, Puerto Rico"
      },
      "geometry": {
        "type": "Point",
        "coordinates": [
          -66.8106666666667,
          17.9843333333333,
          16.16
        ]
      },
      "id": "pr71489583"
    },
    {
      "type": "Feature",
      "properties": {
        "mag": 3.24,
        "place": "65 km N of Tierras Nuevas Poniente, Puerto Rico",
        "time": 1752827330010,
        "updated": 1752829534260,
        "tz": null,
        "url": "https://earthquake.usgs.gov/earthquakes/eventpage/pr71489578",
        "detail": "https://earthquake.usgs.gov/earthquakes/feed/v1.0/detail/pr71489578.geojson",
        "felt": null,
        "cdi": null,
        "mmi": null,
        "alert": null,
        "status": "reviewed",
        "tsunami": 0,
        "sig": 162,
        "net": "pr",
        "code": "71489578",
        "ids": ",pr71489578,",
        "sources": ",pr,",
        "types": ",origin,phase-data,",
        "nst": 12,
        "dmin": 0.5723,
        "rms": 0.22,
        "gap": 280,
        "magType": "md",
        "type": "earthquake",
        "title": "M 3.2 - 65 km N of Tierras Nuevas Poniente, Puerto Rico"
      },
      "geometry": {
        "type": "Point",
        "coordinates": [
          -66.4843333333333,
          19.0508333333333,
          15.42
        ]
      },
      "id": "pr71489578"
    },
    {
      "type": "Feature",
      "properties": {
        "mag": 2.21,
        "place": "10 km S of Gu치nica, Puerto Rico",
        "time": 1752825450590,
        "updated": 1752826804070,
        "tz": null,
        "url": "https://earthquake.usgs.gov/earthquakes/eventpage/pr71489568",
        "detail": "https://earthquake.usgs.gov/earthquakes/feed/v1.0/detail/pr71489568.geojson",
        "felt": null,
        "cdi": null,
        "mmi": null,
        "alert": null,
        "status": "reviewed",
        "tsunami": 0,
        "sig": 75,
        "net": "pr",
        "code": "71489568",
        "ids": ",pr71489568,",
        "sources": ",pr,",
        "types": ",origin,phase-data,",
        "nst": 5,
        "dmin": 0.09501,
        "rms": 0.04,
        "gap": 248,
        "magType": "md",
        "type": "earthquake",
        "title": "M 2.2 - 10 km S of Gu치nica, Puerto Rico"
      },
      "geometry": {
        "type": "Point",
        "coordinates": [
          -66.9168333333333,
          17.877,
          12.9
        ]
      },
      "id": "pr71489568"
    },
    {
      "type": "Feature",
      "properties": {
        "mag": 2.38,
        "place": "0 km S of Indios, Puerto Rico",
        "time": 1752812327060,
        "updated": 1752820107390,
        "tz": null,
        "url": "https://earthquake.usgs.gov/earthquakes/eventpage/pr71489553",
        "detail": "https://earthquake.usgs.gov/earthquakes/feed/v1.0/detail/pr71489553.geojson",
        "felt": null,
        "cdi": null,
        "mmi": null,
        "alert": null,
        "status": "reviewed",
        "tsunami": 0,
        "sig": 87,
        "net": "pr",
        "code": "71489553",
        "ids": ",pr71489553,",
        "sources": ",pr,",
        "types": ",origin,phase-data,",
        "nst": 7,
        "dmin": 0.04824,
        "rms": 0.16,
        "gap": 186,
        "magType": "md",
        "type": "earthquake",
        "title": "M 2.4 - 0 km S of Indios, Puerto Rico"
      },
      "geometry": {
        "type": "Point",
        "coordinates": [
          -66.8196666666667,
          17.986,
          16.36
        ]
      },
      "id": "pr71489553"
    },
    {
      "type": "Feature",
      "properties": {
        "mag": 2.18,
        "place": "2 km SW of Gu치nica, Puerto Rico",
        "time": 1752796445860,
        "updated": 1752797107510,
        "tz": null,
        "url": "https://earthquake.usgs.gov/earthquakes/eventpage/pr71489543",
        "detail": "https://earthquake.usgs.gov/earthquakes/feed/v1.0/detail/pr71489543.geojson",
        "felt": null,
        "cdi": null,
        "mmi": null,
        "alert": null,
        "status": "reviewed",
        "tsunami": 0,
        "sig": 73,
        "net": "pr",
        "code": "71489543",
        "ids": ",pr71489543,",
        "sources": ",pr,",
        "types": ",origin,phase-data,",
        "nst": 10,
        "dmin": 0.04359,
        "rms": 0.17,
        "gap": 204,
        "magType": "md",
        "type": "earthquake",
        "title": "M 2.2 - 2 km SW of Gu치nica, Puerto Rico"
      },
      "geometry": {
        "type": "Point",
        "coordinates": [
          -66.9205,
          17.956,
          14.75
        ]
      },
      "id": "pr71489543"
    },
    {
      "type": "Feature",
      "properties": {
        "mag": 2.65,
        "place": "24 km SSW of Esperanza, Puerto Rico",
        "time": 1752783868970,
        "updated": 1752784848580,
        "tz": null,
        "url": "https://earthquake.usgs.gov/earthquakes/eventpage/pr71489523",
        "detail": "https://earthquake.usgs.gov/earthquakes/feed/v1.0/detail/pr71489523.geojson",
        "felt": null,
        "cdi": null,
        "mmi": null,
        "alert": null,
        "status": "reviewed",
        "tsunami": 0,
        "sig": 108,
        "net": "pr",
        "code": "71489523",
        "ids": ",pr71489523,",
        "sources": ",pr,",
        "types": ",origin,phase-data,",
        "nst": 11,
        "dmin": 0.3364,
        "rms": 0.06,
        "gap": 223,
        "magType": "md",
        "type": "earthquake",
        "title": "M 2.7 - 24 km SSW of Esperanza, Puerto Rico"
      },
      "geometry": {
        "type": "Point",
        "coordinates": [
          -65.5511666666667,
          17.8938333333333,
          36.3
        ]
      },
      "id": "pr71489523"
    },
    {
      "type": "Feature",
      "properties": {
        "mag": 3.22,
        "place": "5 km SE of Espino, Puerto Rico",
        "time": 1752780609560,
        "updated": 1752798380074,
        "tz": null,
        "url": "https://earthquake.usgs.gov/earthquakes/eventpage/pr71489513",
        "detail": "https://earthquake.usgs.gov/earthquakes/feed/v1.0/detail/pr71489513.geojson",
        "felt": 1,
        "cdi": 1,
        "mmi": null,
        "alert": null,
        "status": "reviewed",
        "tsunami": 0,
        "sig": 160,
        "net": "pr",
        "code": "71489513",
        "ids": ",pr71489513,",
        "sources": ",pr,",
        "types": ",dyfi,origin,phase-data,",
        "nst": 22,
        "dmin": 0.0667,
        "rms": 0.33,
        "gap": 60,
        "magType": "md",
        "type": "earthquake",
        "title": "M 3.2 - 5 km SE of Espino, Puerto Rico"
      },
      "geometry": {
        "type": "Point",
        "coordinates": [
          -67.0781666666667,
          18.249,
          27.12
        ]
      },
      "id": "pr71489513"
    },
    {
      "type": "Feature",
      "properties": {
        "mag": 2.12,
        "place": "2 km N of Santa Clara, Puerto Rico",
        "time": 1752779929460,
        "updated": 1752781176580,
        "tz": null,
        "url": "https://earthquake.usgs.gov/earthquakes/eventpage/pr71489508",
        "detail": "https://earthquake.usgs.gov/earthquakes/feed/v1.0/detail/pr71489508.geojson",
        "felt": null,
        "cdi": null,
        "mmi": null,
        "alert": null,
        "status": "reviewed",
        "tsunami": 0,
        "sig": 69,
        "net": "pr",
        "code": "71489508",
        "ids": ",pr71489508,",
        "sources": ",pr,",
        "types": ",origin,phase-data,",
        "nst": 5,
        "dmin": 0.2391,
        "rms": 0.11,
        "gap": 179,
        "magType": "md",
        "type": "earthquake",
        "title": "M 2.1 - 2 km N of Santa Clara, Puerto Rico"
      },
      "geometry": {
        "type": "Point",
        "coordinates": [
          -66.1261666666667,
          18.2371666666667,
          33.49
        ]
      },
      "id": "pr71489508"
    }
  ],
  "bbox": [
    -179.7792,
    -62.7065,
    -2.1099998950958,
    179.9185,
    65.2278,
    625.437
  ]
}
