{
  "type": "FeatureCollection",
  "metadata": {
    "generated": 1755798287000,
    "url": "https://earthquake.usgs.gov/earthquakes/feed/v1.0/summary/all_day.geojson",
    "title": "USGS All Earthquakes, Past Day",
    "status": 200,
    "api": "1.14.1",
    "count": 279
  },
  "features": [
    {
      "type": "Feature",
      "properties": {
        "mag": 2.23,
        "place": "5 km SW of Fuig, Puerto Rico",
        "time": 1755776480230,
        "updated": 1755777959320,
        "tz": null,
        "url": "https://earthquake.usgs.gov/earthquakes/eventpage/pr71493233",
        "detail": "https://earthquake.usgs.gov/earthquakes/feed/v1.0/detail/pr71493233.geojson",
        "felt": null,
        "cdi": null,
        "mmi": null,
        "alert": null,
        "status": "reviewed",
        "tsunami": 0,
        "sig": 77,
        "net": "pr",
        "code": "71493233",
        "ids": ",pr71493233,",
        "sources": ",pr,",
        "types": ",origin,phase-data,",
        "nst": 11,
        "dmin": 0.0779,
        "rms": 0.11,
        "gap": 199,
        "magType": "md",
        "type": "earthquake",
        "title": "M 2.2 - 5 km SW of Fuig, Puerto Rico"
      },
      "geometry": {
        "type": "Point",
        "coordinates": [
          -66.9595,
          17.9596666666667,
          13.49
        ]
      },
      "id": "pr71493233"
    },
    {
      "type": "Feature",
      "properties": {
        "mag": 2.32,
        "place": "1 km ESE of Indios, Puerto Rico",
        "time": 1755775473310,
        "updated": 1755776686140,
        "tz": null,
        "url": "https://earthquake.usgs.gov/earthquakes/eventpage/pr71493213",
        "detail": "https://earthquake.usgs.gov/earthquakes/feed/v1.0/detail/pr71493213.geojson",
        "felt": null,
        "cdi": null,
        "mmi": null,
        "alert": null,
        "status": "reviewed",
        "tsunami": 0,
        "sig": 83,
        "net": "pr",
        "code": "71493213",
        "ids": ",pr71493213,",
        "sources": ",pr,",
        "types": ",origin,phase-data,",
        "nst": 11,
        "dmin": 0.03408,
        "rms": 0.36,
        "gap": 187,
        "magType": "md",
        "type": "earthquake",
        "title": "M 2.3 - 1 km ESE of Indios, Puerto Rico"
      },
      "geometry": {
        "type": "Point",
        "coordinates": [
          -66.8043333333333,
          17.988,
          12.74
        ]
      },
      "id": "pr71493213"
    },
    {
      "type": "Feature",
      "properties": {
        "mag": 2.23,
        "place": "3 km W of Fuig, Puerto Rico",
        "time": 1755769828820,
        "updated": 1755770215760,
        "tz": null,
        "url": "https://earthquake.usgs.gov/earthquakes/eventpage/pr71493193",
        "detail": "https://earthquake.usgs.gov/earthquakes/feed/v1.0/detail/pr71493193.geojson",
        "felt": null,
        "cdi": null,
        "mmi": null,
        "alert": null,
        "status": "reviewed",
        "tsunami": 0,
        "sig": 77,
        "net": "pr",
        "code": "71493193",
        "ids": ",pr71493193,",
        "sources": ",pr,",
        "types": ",origin,phase-data,",
        "nst": 10,
        "dmin": 0.0431,
        "rms": 0.16,
        "gap": 151,
        "magType": "md",
        "type": "earthquake",
        "title": "M 2.2 - 3 km W of Fuig, Puerto Rico"
      },
      "geometry": {
        "type": "Point",
        "coordinates": [
          -66.9513333333333,
          17.9866666666667,
          10.17
        ]
      },
      "id": "pr71493193"
    },
    {
      "type": "Feature",
      "properties": {
        "mag": 3.57,
        "place": "39 km SSE of Boca de Yuma, Dominican Republic",
        "time": 1755767985280,
        "updated": 1755770463809,
        "tz": null,
        "url": "https://earthquake.usgs.gov/earthquakes/eventpage/pr2025233002",
        "detail": "https://earthquake.usgs.gov/earthquakes/feed/v1.0/detail/pr2025233002.geojson",
        "felt": null,
        "cdi": null,
        "mmi": null,
        "alert": null,
        "status": "reviewed",
        "tsunami": 0,
        "sig": 196,
        "net": "pr",
        "code": "2025233002",
        "ids": ",pr2025233002,",
        "sources": ",pr,",
        "types": ",origin,phase-data,",
        "nst": 11,
        "dmin": 0.4877,
        "rms": 0.45,
        "gap": 220,
        "magType": "md",
        "type": "earthquake",
        "title": "M 3.6 - 39 km SSE of Boca de Yuma, Dominican Republic"
      },
      "geometry": {
        "type": "Point",
        "coordinates": [
          -68.4978,
          18.0403,
          66
        ]
      },
      "id": "pr2025233002"
    },
    {
      "type": "Feature",
      "properties": {
        "mag": 2.24,
        "place": "1 km W of Gu치nica, Puerto Rico",
        "time": 1755762829050,
        "updated": 1755763344190,
        "tz": null,
        "url": "https://earthquake.usgs.gov/earthquakes/eventpage/pr71493183",
        "detail": "https://earthquake.usgs.gov/earthquakes/feed/v1.0/detail/pr71493183.geojson",
        "felt": null,
        "cdi": null,
        "mmi": null,
        "alert": null,
        "status": "reviewed",
        "tsunami": 0,
        "sig": 77,
        "net": "pr",
        "code": "71493183",
        "ids": ",pr71493183,",
        "sources": ",pr,",
        "types": ",origin,phase-data,",
        "nst": 8,
        "dmin": 0.04353,
        "rms": 0.3,
        "gap": 187,
        "magType": "md",
        "type": "earthquake",
        "title": "M 2.2 - 1 km W of Gu치nica, Puerto Rico"
      },
      "geometry": {
        "type": "Point",
        "coordinates": [
          -66.9246666666667,
          17.9698333333333,
          9.12
        ]
      },
      "id": "pr71493183"
    },
    {
      "type": "Feature",
      "properties": {
        "mag": 2.71,
        "place": "1 km S of Gu치nica, Puerto Rico",
        "time": 1755757777410,
        "updated": 1755758887920,
        "tz": null,
        "url": "https://earthquake.usgs.gov/earthquakes/eventpage/pr71493173",
        "detail": "https://earthquake.usgs.gov/earthquakes/feed/v1.0/detail/pr71493173.geojson",
        "felt": null,
        "cdi": null,
        "mmi": null,
        "alert": null,
        "status": "reviewed",
        "tsunami": 0,
        "sig": 113,
        "net": "pr",
        "code": "71493173",
        "ids": ",pr71493173,",
        "sources": ",pr,",
        "types": ",origin,phase-data,",
        "nst": 11,
        "dmin": 0.03545,
        "rms": 0.19,
        "gap": 204,
        "magType": "md",
        "type": "earthquake",
        "title": "M 2.7 - 1 km S of Gu치nica, Puerto Rico"
      },
      "geometry": {
        "type": "Point",
        "coordinates": [
          -66.9101666666667,
          17.9551666666667,
          10.62
        ]
      },
      "id": "pr71493173"
    },
    {
      "type": "Feature",
      "properties": {
        "mag": 3.85,
        "place": "123 km SSE of Boca de Yuma, Dominican Republic",
        "time": 1755741320120,
        "updated": 1755743257430,
        "tz": null,
        "url": "https://earthquake.usgs.gov/earthquakes/eventpage/pr2025233001",
        "detail": "https://earthquake.usgs.gov/earthquakes/feed/v1.0/detail/pr2025233001.geojson",
        "felt": null,
        "cdi": null,
        "mmi": null,
        "alert": null,
        "status": "reviewed",
        "tsunami": 0,
        "sig": 228,
        "net": "pr",
        "code": "2025233001",
        "ids": ",pr2025233001,",
        "sources": ",pr,",
        "types": ",origin,phase-data,",
        "nst": 23,
        "dmin": 1.2155,
        "rms": 0.46,
        "gap": 254,
        "magType": "md",
        "type": "earthquake",
        "title": "M 3.9 - 123 km SSE of Boca de Yuma, Dominican Republic"
      },
      "geometry": {
        "type": "Point",
        "coordinates": [
          -68.2925,
          17.3016,
          70
        ]
      },
      "id": "pr2025233001"
    },
    {
      "type": "Feature",
      "properties": {
        "mag": 2.12,
        "place": "6 km SE of Maria Antonia, Puerto Rico",
        "time": 1755740092950,
        "updated": 1755740757900,
        "tz": null,
        "url": "https://earthquake.usgs.gov/earthquakes/eventpage/pr71493148",
        "detail": "https://earthquake.usgs.gov/earthquakes/feed/v1.0/detail/pr71493148.geojson",
        "felt": null,
        "cdi": null,
        "mmi": null,
        "alert": null,
        "status": "reviewed",
        "tsunami": 0,
        "sig": 69,
        "net": "pr",
        "code": "71493148",
        "ids": ",pr71493148,",
        "sources": ",pr,",
        "types": ",origin,phase-data,",
        "nst": 8,
        "dmin": 0.04539,
        "rms": 0.08,
        "gap": 223,
        "magType": "md",
        "type": "earthquake",
        "title": "M 2.1 - 6 km SE of Maria Antonia, Puerto Rico"
      },
      "geometry": {
        "type": "Point",
        "coordinates": [
          -66.8525,
          17.9293333333333,
          10.2
        ]
      },
      "id": "pr71493148"
    },
    {
      "type": "Feature",
      "properties": {
        "mag": 2.05,
        "place": "1 km NNW of Guayanilla, Puerto Rico",
        "time": 1755736961710,
        "updated": 1755738497070,
        "tz": null,
        "url": "https://earthquake.usgs.gov/earthquakes/eventpage/pr71493143",
        "detail": "https://earthquake.usgs.gov/earthquakes/feed/v1.0/detail/pr71493143.geojson",
        "felt": null,
        "cdi": null,
        "mmi": null,
        "alert": null,
        "status": "reviewed",
        "tsunami": 0,
        "sig": 65,
        "net": "pr",
        "code": "71493143",
        "ids": ",pr71493143,",
        "sources": ",pr,",
        "types": ",origin,phase-data,",
        "nst": 11,
        "dmin": 0.09092,
        "rms": 0.12,
        "gap": 143,
        "magType": "md",
        "type": "earthquake",
        "title": "M 2.1 - 1 km NNW of Guayanilla, Puerto Rico"
      },
      "geometry": {
        "type": "Point",
        "coordinates": [
          -66.7963333333333,
          18.0325,
          17.71
        ]
      },
      "id": "pr71493143"
    },
    {
      "type": "Feature",
      "properties": {
        "mag": 3.62,
        "place": "103 km N of Cruz Bay, U.S. Virgin Islands",
        "time": 1755734695610,
        "updated": 1755736683827,
        "tz": null,
        "url": "https://earthquake.usgs.gov/earthquakes/eventpage/pr2025233000",
        "detail": "https://earthquake.usgs.gov/earthquakes/feed/v1.0/detail/pr2025233000.geojson",
        "felt": null,
        "cdi": null,
        "mmi": null,
        "alert": null,
        "status": "reviewed",
        "tsunami": 0,
        "sig": 202,
        "net": "pr",
        "code": "2025233000",
        "ids": ",pr2025233000,",
        "sources": ",pr,",
        "types": ",origin,phase-data,",
        "nst": 9,
        "dmin": 0.8438,
        "rms": 0.29,
        "gap": 273,
        "magType": "md",
        "type": "earthquake",
        "title": "M 3.6 - 103 km N of Cruz Bay, U.S. Virgin Islands"
      },
      "geometry": {
        "type": "Point",
        "coordinates": [
          -64.7308,
          19.2678,
          52
        ]
      },
      "id": "pr2025233000"
    }
  ],
  "bbox": [
    -175.1125,
    -21.5995,
    -2,
    160.0448,
    65.4409,
    248.744
  ]
}
