{
  "type": "FeatureCollection",
  "metadata": {
    "generated": 1759066380000,
    "url": "https://earthquake.usgs.gov/earthquakes/feed/v1.0/summary/all_day.geojson",
    "title": "USGS All Earthquakes, Past Day",
    "status": 200,
    "api": "1.14.1",
    "count": 155
  },
  "features": [
    {
      "type": "Feature",
      "properties": {
        "mag": 2.2,
        "place": "17 km SSE of Gu치nica, Puerto Rico",
        "time": 1759039568780,
        "updated": 1759040200040,
        "tz": null,
        "url": "https://earthquake.usgs.gov/earthquakes/eventpage/pr71496668",
        "detail": "https://earthquake.usgs.gov/earthquakes/feed/v1.0/detail/pr71496668.geojson",
        "felt": null,
        "cdi": null,
        "mmi": null,
        "alert": null,
        "status": "reviewed",
        "tsunami": 0,
        "sig": 74,
        "net": "pr",
        "code": "71496668",
        "ids": ",pr71496668,",
        "sources": ",pr,",
        "types": ",origin,phase-data,",
        "nst": 6,
        "dmin": 0.1539,
        "rms": 0.18,
        "gap": 232,
        "magType": "md",
        "type": "earthquake",
        "title": "M 2.2 - 17 km SSE of Gu치nica, Puerto Rico"
      },
      "geometry": {
        "type": "Point",
        "coordinates": [
          -66.8763333333333,
          17.8203333333333,
          15.32
        ]
      },
      "id": "pr71496668"
    },
    {
      "type": "Feature",
      "properties": {
        "mag": 2.89,
        "place": "18 km S of Gu치nica, Puerto Rico",
        "time": 1759038094820,
        "updated": 1759039325680,
        "tz": null,
        "url": "https://earthquake.usgs.gov/earthquakes/eventpage/pr71496648",
        "detail": "https://earthquake.usgs.gov/earthquakes/feed/v1.0/detail/pr71496648.geojson",
        "felt": null,
        "cdi": null,
        "mmi": null,
        "alert": null,
        "status": "reviewed",
        "tsunami": 0,
        "sig": 128,
        "net": "pr",
        "code": "71496648",
        "ids": ",pr71496648,",
        "sources": ",pr,",
        "types": ",origin,phase-data,",
        "nst": 19,
        "dmin": 0.1681,
        "rms": 0.37,
        "gap": 236,
        "magType": "md",
        "type": "earthquake",
        "title": "M 2.9 - 18 km S of Gu치nica, Puerto Rico"
      },
      "geometry": {
        "type": "Point",
        "coordinates": [
          -66.8785,
          17.8056666666667,
          9.12
        ]
      },
      "id": "pr71496648"
    },
    {
      "type": "Feature",
      "properties": {
        "mag": 3.39,
        "place": "59 km N of Charlotte Amalie, U.S. Virgin Islands",
        "time": 1759011757110,
        "updated": 1759016767040,
        "tz": null,
        "url": "https://earthquake.usgs.gov/earthquakes/eventpage/pr71496633",
        "detail": "https://earthquake.usgs.gov/earthquakes/feed/v1.0/detail/pr71496633.geojson",
        "felt": null,
        "cdi": null,
        "mmi": null,
        "alert": null,
        "status": "reviewed",
        "tsunami": 0,
        "sig": 177,
        "net": "pr",
        "code": "71496633",
        "ids": ",us6000rdde,pr71496633,",
        "sources": ",us,pr,",
        "types": ",origin,phase-data,",
        "nst": 19,
        "dmin": 0.5517,
        "rms": 0.26,
        "gap": 227,
        "magType": "md",
        "type": "earthquake",
        "title": "M 3.4 - 59 km N of Charlotte Amalie, U.S. Virgin Islands"
      },
      "geometry": {
        "type": "Point",
        "coordinates": [
          -64.9441666666667,
          18.881,
          21.7
        ]
      },
      "id": "pr71496633"
    },
    {
      "type": "Feature",
      "properties": {
        "mag": 3.4,
        "place": "54 km NNW of San Antonio, Puerto Rico",
        "time": 1758988865490,
        "updated": 1758992379040,
        "tz": null,
        "url": "https://earthquake.usgs.gov/earthquakes/eventpage/pr71496623",
        "detail": "https://earthquake.usgs.gov/earthquakes/feed/v1.0/detail/pr71496623.geojson",
        "felt": null,
        "cdi": null,
        "mmi": null,
        "alert": null,
        "status": "reviewed",
        "tsunami": 0,
        "sig": 178,
        "net": "pr",
        "code": "71496623",
        "ids": ",us6000rdcf,pr71496623,",
        "sources": ",us,pr,",
        "types": ",origin,phase-data,",
        "nst": 28,
        "dmin": 0.5109,
        "rms": 0.31,
        "gap": 176,
        "magType": "md",
        "type": "earthquake",
        "title": "M 3.4 - 54 km NNW of San Antonio, Puerto Rico"
      },
      "geometry": {
        "type": "Point",
        "coordinates": [
          -67.3381666666667,
          18.9333333333333,
          6.24
        ]
      },
      "id": "pr71496623"
    }
  ],
  "bbox": [
    -175.7405,
    -29.1489,
    -0.75999999046326,
    178.842,
    64.9832,
    556.297
  ]
}
