{
  "type": "FeatureCollection",
  "metadata": {
    "generated": 1771544811000,
    "url": "https://earthquake.usgs.gov/earthquakes/feed/v1.0/summary/all_day.geojson",
    "title": "USGS All Earthquakes, Past Day",
    "status": 200,
    "api": "1.14.1",
    "count": 248
  },
  "features": [
    {
      "type": "Feature",
      "properties": {
        "mag": 2.25,
        "place": "2 km WSW of Gu치nica, Puerto Rico",
        "time": 1771542587250,
        "updated": 1771543526420,
        "tz": null,
        "url": "https://earthquake.usgs.gov/earthquakes/eventpage/pr71508308",
        "detail": "https://earthquake.usgs.gov/earthquakes/feed/v1.0/detail/pr71508308.geojson",
        "felt": null,
        "cdi": null,
        "mmi": null,
        "alert": null,
        "status": "reviewed",
        "tsunami": 0,
        "sig": 78,
        "net": "pr",
        "code": "71508308",
        "ids": ",pr71508308,",
        "sources": ",pr,",
        "types": ",origin,phase-data,",
        "nst": 3,
        "dmin": 0.05191,
        "rms": 0.03,
        "gap": 193,
        "magType": "md",
        "type": "earthquake",
        "title": "M 2.3 - 2 km WSW of Gu치nica, Puerto Rico"
      },
      "geometry": {
        "type": "Point",
        "coordinates": [
          -66.933,
          17.9661666666667,
          15.49
        ]
      },
      "id": "pr71508308"
    },
    {
      "type": "Feature",
      "properties": {
        "mag": 2.23,
        "place": "0 km ESE of Gu치nica, Puerto Rico",
        "time": 1771532778790,
        "updated": 1771533499880,
        "tz": null,
        "url": "https://earthquake.usgs.gov/earthquakes/eventpage/pr71508293",
        "detail": "https://earthquake.usgs.gov/earthquakes/feed/v1.0/detail/pr71508293.geojson",
        "felt": null,
        "cdi": null,
        "mmi": null,
        "alert": null,
        "status": "reviewed",
        "tsunami": 0,
        "sig": 77,
        "net": "pr",
        "code": "71508293",
        "ids": ",pr71508293,",
        "sources": ",pr,",
        "types": ",origin,phase-data,",
        "nst": 7,
        "dmin": 0.008003,
        "rms": 0.15,
        "gap": 196,
        "magType": "md",
        "type": "earthquake",
        "title": "M 2.2 - 0 km ESE of Gu치nica, Puerto Rico"
      },
      "geometry": {
        "type": "Point",
        "coordinates": [
          -66.9006666666667,
          17.9696666666667,
          10.85
        ]
      },
      "id": "pr71508293"
    },
    {
      "type": "Feature",
      "properties": {
        "mag": 5.1,
        "place": "155 km N of Arecibo, Puerto Rico",
        "time": 1771510686650,
        "updated": 1771529488112,
        "tz": null,
        "url": "https://earthquake.usgs.gov/earthquakes/eventpage/pr2026050001",
        "detail": "https://earthquake.usgs.gov/earthquakes/feed/v1.0/detail/pr2026050001.geojson",
        "felt": 36,
        "cdi": 4.3,
        "mmi": null,
        "alert": null,
        "status": "reviewed",
        "tsunami": 1,
        "sig": 416,
        "net": "pr",
        "code": "2026050001",
        "ids": ",at00tapme6,us6000sa6k,pr2026050001,",
        "sources": ",at,us,pr,",
        "types": ",dyfi,impact-link,origin,phase-data,",
        "nst": 32,
        "dmin": 1.3941,
        "rms": 0.34,
        "gap": 220,
        "magType": "ml",
        "type": "earthquake",
        "title": "M 5.1 - 155 km N of Arecibo, Puerto Rico"
      },
      "geometry": {
        "type": "Point",
        "coordinates": [
          -66.5455,
          19.8711,
          34
        ]
      },
      "id": "pr2026050001"
    },
    {
      "type": "Feature",
      "properties": {
        "mag": 3.75,
        "place": "49 km S of La Romana, Dominican Republic",
        "time": 1771475884210,
        "updated": 1771479148040,
        "tz": null,
        "url": "https://earthquake.usgs.gov/earthquakes/eventpage/pr2026050000",
        "detail": "https://earthquake.usgs.gov/earthquakes/feed/v1.0/detail/pr2026050000.geojson",
        "felt": null,
        "cdi": null,
        "mmi": null,
        "alert": null,
        "status": "reviewed",
        "tsunami": 0,
        "sig": 216,
        "net": "pr",
        "code": "2026050000",
        "ids": ",us6000sa4a,pr2026050000,",
        "sources": ",us,pr,",
        "types": ",origin,phase-data,",
        "nst": 18,
        "dmin": 0.7666,
        "rms": 0.44,
        "gap": 243,
        "magType": "md",
        "type": "earthquake",
        "title": "M 3.8 - 49 km S of La Romana, Dominican Republic"
      },
      "geometry": {
        "type": "Point",
        "coordinates": [
          -68.936,
          17.9846,
          99
        ]
      },
      "id": "pr2026050000"
    },
    {
      "type": "Feature",
      "properties": {
        "mag": 2.45,
        "place": "2 km NW of Guayanilla, Puerto Rico",
        "time": 1771470136800,
        "updated": 1771471115710,
        "tz": null,
        "url": "https://earthquake.usgs.gov/earthquakes/eventpage/pr71508248",
        "detail": "https://earthquake.usgs.gov/earthquakes/feed/v1.0/detail/pr71508248.geojson",
        "felt": null,
        "cdi": null,
        "mmi": null,
        "alert": null,
        "status": "reviewed",
        "tsunami": 0,
        "sig": 92,
        "net": "pr",
        "code": "71508248",
        "ids": ",pr71508248,",
        "sources": ",pr,",
        "types": ",origin,phase-data,",
        "nst": 14,
        "dmin": 0.02608,
        "rms": 0.22,
        "gap": 92,
        "magType": "md",
        "type": "earthquake",
        "title": "M 2.5 - 2 km NW of Guayanilla, Puerto Rico"
      },
      "geometry": {
        "type": "Point",
        "coordinates": [
          -66.8128333333333,
          18.0365,
          15.81
        ]
      },
      "id": "pr71508248"
    },
    {
      "type": "Feature",
      "properties": {
        "mag": 4.7,
        "place": "29 km S of La Conquista, Nicaragua",
        "time": 1771470009777,
        "updated": 1771531892080,
        "tz": null,
        "url": "https://earthquake.usgs.gov/earthquakes/eventpage/us6000sa3l",
        "detail": "https://earthquake.usgs.gov/earthquakes/feed/v1.0/detail/us6000sa3l.geojson",
        "felt": 22,
        "cdi": 3.6,
        "mmi": null,
        "alert": null,
        "status": "reviewed",
        "tsunami": 0,
        "sig": 348,
        "net": "us",
        "code": "6000sa3l",
        "ids": ",us6000sa3l,",
        "sources": ",us,",
        "types": ",dyfi,origin,phase-data,",
        "nst": 77,
        "dmin": 1.07,
        "rms": 1.38,
        "gap": 134,
        "magType": "mww",
        "type": "earthquake",
        "title": "M 4.7 - 29 km S of La Conquista, Nicaragua"
      },
      "geometry": {
        "type": "Point",
        "coordinates": [
          -86.2297,
          11.4685,
          84.336
        ]
      },
      "id": "us6000sa3l"
    },
    {
      "type": "Feature",
      "properties": {
        "mag": 2.22,
        "place": "4 km WSW of Fuig, Puerto Rico",
        "time": 1771468613150,
        "updated": 1771469259980,
        "tz": null,
        "url": "https://earthquake.usgs.gov/earthquakes/eventpage/pr71508243",
        "detail": "https://earthquake.usgs.gov/earthquakes/feed/v1.0/detail/pr71508243.geojson",
        "felt": null,
        "cdi": null,
        "mmi": null,
        "alert": null,
        "status": "reviewed",
        "tsunami": 0,
        "sig": 76,
        "net": "pr",
        "code": "71508243",
        "ids": ",pr71508243,",
        "sources": ",pr,",
        "types": ",origin,phase-data,",
        "nst": 10,
        "dmin": 0.0472,
        "rms": 0.12,
        "gap": 182,
        "magType": "md",
        "type": "earthquake",
        "title": "M 2.2 - 4 km WSW of Fuig, Puerto Rico"
      },
      "geometry": {
        "type": "Point",
        "coordinates": [
          -66.9581666666667,
          17.9696666666667,
          13.82
        ]
      },
      "id": "pr71508243"
    },
    {
      "type": "Feature",
      "properties": {
        "mag": 1.86,
        "place": "6 km SW of Fuig, Puerto Rico",
        "time": 1771459133940,
        "updated": 1771459707750,
        "tz": null,
        "url": "https://earthquake.usgs.gov/earthquakes/eventpage/pr71508228",
        "detail": "https://earthquake.usgs.gov/earthquakes/feed/v1.0/detail/pr71508228.geojson",
        "felt": null,
        "cdi": null,
        "mmi": null,
        "alert": null,
        "status": "reviewed",
        "tsunami": 0,
        "sig": 53,
        "net": "pr",
        "code": "71508228",
        "ids": ",pr71508228,",
        "sources": ",pr,",
        "types": ",origin,phase-data,",
        "nst": 10,
        "dmin": 0.05993,
        "rms": 0.16,
        "gap": 204,
        "magType": "md",
        "type": "earthquake",
        "title": "M 1.9 - 6 km SW of Fuig, Puerto Rico"
      },
      "geometry": {
        "type": "Point",
        "coordinates": [
          -66.9686666666667,
          17.954,
          13.76
        ]
      },
      "id": "pr71508228"
    }
  ],
  "bbox": [
    -179.9581,
    -39.5847,
    -0.74000000953674,
    179.708,
    63.857,
    590.024
  ]
}
