{
  "type": "FeatureCollection",
  "metadata": {
    "generated": 1774882534000,
    "url": "https://earthquake.usgs.gov/earthquakes/feed/v1.0/summary/all_day.geojson",
    "title": "USGS All Earthquakes, Past Day",
    "status": 200,
    "api": "2.3.0",
    "count": 302
  },
  "features": [
    {
      "type": "Feature",
      "properties": {
        "mag": 3.01,
        "place": "16 km NNE of Isabela, Puerto Rico",
        "time": 1774862796900,
        "updated": 1774867491110,
        "tz": null,
        "url": "https://earthquake.usgs.gov/earthquakes/eventpage/pr71511393",
        "detail": "https://earthquake.usgs.gov/earthquakes/feed/v1.0/detail/pr71511393.geojson",
        "felt": null,
        "cdi": null,
        "mmi": null,
        "alert": null,
        "status": "reviewed",
        "tsunami": 0,
        "sig": 139,
        "net": "pr",
        "code": "71511393",
        "ids": ",pr71511393,",
        "sources": ",pr,",
        "types": ",origin,phase-data,",
        "nst": 4,
        "dmin": 0.2268,
        "rms": 0.11,
        "gap": 283,
        "magType": "md",
        "type": "earthquake",
        "title": "M 3.0 - 16 km NNE of Isabela, Puerto Rico"
      },
      "geometry": {
        "type": "Point",
        "coordinates": [
          -66.948,
          18.6341666666667,
          8.79
        ]
      },
      "id": "pr71511393"
    },
    {
      "type": "Feature",
      "properties": {
        "mag": 3.94,
        "place": "50 km NNW of San Antonio, Puerto Rico",
        "time": 1774862373390,
        "updated": 1774865532963,
        "tz": null,
        "url": "https://earthquake.usgs.gov/earthquakes/eventpage/pr2026089000",
        "detail": "https://earthquake.usgs.gov/earthquakes/feed/v1.0/detail/pr2026089000.geojson",
        "felt": null,
        "cdi": null,
        "mmi": null,
        "alert": null,
        "status": "reviewed",
        "tsunami": 0,
        "sig": 239,
        "net": "pr",
        "code": "2026089000",
        "ids": ",us7000s8qr,pr2026089000,",
        "sources": ",us,pr,",
        "types": ",origin,phase-data,",
        "nst": 24,
        "dmin": 0.4768,
        "rms": 0.45,
        "gap": 199,
        "magType": "md",
        "type": "earthquake",
        "title": "M 3.9 - 50 km NNW of San Antonio, Puerto Rico"
      },
      "geometry": {
        "type": "Point",
        "coordinates": [
          -67.355,
          18.8773,
          12
        ]
      },
      "id": "pr2026089000"
    },
    {
      "type": "Feature",
      "properties": {
        "mag": 5.4,
        "place": "58 km SW of Masachapa, Nicaragua",
        "time": 1774855828018,
        "updated": 1774864600020,
        "tz": null,
        "url": "https://earthquake.usgs.gov/earthquakes/eventpage/us7000s8pl",
        "detail": "https://earthquake.usgs.gov/earthquakes/feed/v1.0/detail/us7000s8pl.geojson",
        "felt": null,
        "cdi": null,
        "mmi": 4.166,
        "alert": "green",
        "status": "reviewed",
        "tsunami": 0,
        "sig": 449,
        "net": "us",
        "code": "7000s8pl",
        "ids": ",us7000s8pl,",
        "sources": ",us,",
        "types": ",losspager,origin,phase-data,shakemap,",
        "nst": 78,
        "dmin": 1.632,
        "rms": 1.27,
        "gap": 150,
        "magType": "mww",
        "type": "earthquake",
        "title": "M 5.4 - 58 km SW of Masachapa, Nicaragua"
      },
      "geometry": {
        "type": "Point",
        "coordinates": [
          -86.8927,
          11.4154,
          57.537
        ]
      },
      "id": "us7000s8pl"
    },
    {
      "type": "Feature",
      "properties": {
        "mag": 3.42,
        "place": "106 km N of Cruz Bay, U.S. Virgin Islands",
        "time": 1774844989510,
        "updated": 1774846129450,
        "tz": null,
        "url": "https://earthquake.usgs.gov/earthquakes/eventpage/pr71511338",
        "detail": "https://earthquake.usgs.gov/earthquakes/feed/v1.0/detail/pr71511338.geojson",
        "felt": null,
        "cdi": null,
        "mmi": null,
        "alert": null,
        "status": "reviewed",
        "tsunami": 0,
        "sig": 180,
        "net": "pr",
        "code": "71511338",
        "ids": ",pr71511338,",
        "sources": ",pr,",
        "types": ",origin,phase-data,",
        "nst": 11,
        "dmin": 0.8634,
        "rms": 0.49,
        "gap": 273,
        "magType": "md",
        "type": "earthquake",
        "title": "M 3.4 - 106 km N of Cruz Bay, U.S. Virgin Islands"
      },
      "geometry": {
        "type": "Point",
        "coordinates": [
          -64.745,
          19.2946666666667,
          51.56
        ]
      },
      "id": "pr71511338"
    },
    {
      "type": "Feature",
      "properties": {
        "mag": 3.16,
        "place": "57 km N of Charlotte Amalie, U.S. Virgin Islands",
        "time": 1774817543560,
        "updated": 1774818845330,
        "tz": null,
        "url": "https://earthquake.usgs.gov/earthquakes/eventpage/pr71511318",
        "detail": "https://earthquake.usgs.gov/earthquakes/feed/v1.0/detail/pr71511318.geojson",
        "felt": null,
        "cdi": null,
        "mmi": null,
        "alert": null,
        "status": "reviewed",
        "tsunami": 0,
        "sig": 154,
        "net": "pr",
        "code": "71511318",
        "ids": ",pr71511318,",
        "sources": ",pr,",
        "types": ",origin,phase-data,",
        "nst": 10,
        "dmin": 0.5003,
        "rms": 0.47,
        "gap": 234,
        "magType": "md",
        "type": "earthquake",
        "title": "M 3.2 - 57 km N of Charlotte Amalie, U.S. Virgin Islands"
      },
      "geometry": {
        "type": "Point",
        "coordinates": [
          -64.874,
          18.8611666666667,
          87.95
        ]
      },
      "id": "pr71511318"
    },
    {
      "type": "Feature",
      "properties": {
        "mag": 1.17,
        "place": "3 km W of Olimpo, Puerto Rico",
        "time": 1774805199070,
        "updated": 1774806032240,
        "tz": null,
        "url": "https://earthquake.usgs.gov/earthquakes/eventpage/pr71511313",
        "detail": "https://earthquake.usgs.gov/earthquakes/feed/v1.0/detail/pr71511313.geojson",
        "felt": null,
        "cdi": null,
        "mmi": null,
        "alert": null,
        "status": "reviewed",
        "tsunami": 0,
        "sig": 21,
        "net": "pr",
        "code": "71511313",
        "ids": ",pr71511313,",
        "sources": ",pr,",
        "types": ",origin,phase-data,",
        "nst": 4,
        "dmin": 0.05619,
        "rms": 0.15,
        "gap": 145,
        "magType": "md",
        "type": "earthquake",
        "title": "M 1.2 - 3 km W of Olimpo, Puerto Rico"
      },
      "geometry": {
        "type": "Point",
        "coordinates": [
          -66.1453333333333,
          18.0083333333333,
          9.8
        ]
      },
      "id": "pr71511313"
    },
    {
      "type": "Feature",
      "properties": {
        "mag": 3.69,
        "place": "29 km NNW of Otra Banda, Dominican Republic",
        "time": 1774798422190,
        "updated": 1774802400428,
        "tz": null,
        "url": "https://earthquake.usgs.gov/earthquakes/eventpage/pr2026088001",
        "detail": "https://earthquake.usgs.gov/earthquakes/feed/v1.0/detail/pr2026088001.geojson",
        "felt": null,
        "cdi": null,
        "mmi": null,
        "alert": null,
        "status": "reviewed",
        "tsunami": 0,
        "sig": 209,
        "net": "pr",
        "code": "2026088001",
        "ids": ",us7000s8jz,pr2026088001,",
        "sources": ",us,pr,",
        "types": ",origin,phase-data,",
        "nst": 20,
        "dmin": 0.5471,
        "rms": 0.53,
        "gap": 149,
        "magType": "md",
        "type": "earthquake",
        "title": "M 3.7 - 29 km NNW of Otra Banda, Dominican Republic"
      },
      "geometry": {
        "type": "Point",
        "coordinates": [
          -68.7705,
          18.8985,
          102
        ]
      },
      "id": "pr2026088001"
    }
  ],
  "bbox": [
    -175.6082,
    -47.8194,
    -0.8299999833107,
    176.4725,
    66.8,
    206.036
  ]
}
