{
  "type": "FeatureCollection",
  "metadata": {
    "generated": 1767310490000,
    "url": "https://earthquake.usgs.gov/earthquakes/feed/v1.0/summary/all_day.geojson",
    "title": "USGS All Earthquakes, Past Day",
    "status": 200,
    "api": "1.14.1",
    "count": 245
  },
  "features": [
    {
      "type": "Feature",
      "properties": {
        "mag": 1.81,
        "place": "2 km E of Magas Arriba, Puerto Rico",
        "time": 1767309406590,
        "updated": 1767310377750,
        "tz": null,
        "url": "https://earthquake.usgs.gov/earthquakes/eventpage/pr71503673",
        "detail": "https://earthquake.usgs.gov/earthquakes/feed/v1.0/detail/pr71503673.geojson",
        "felt": null,
        "cdi": null,
        "mmi": null,
        "alert": null,
        "status": "reviewed",
        "tsunami": 0,
        "sig": 50,
        "net": "pr",
        "code": "71503673",
        "ids": ",pr71503673,",
        "sources": ",pr,",
        "types": ",origin,phase-data,",
        "nst": 6,
        "dmin": 0.129,
        "rms": 0.21,
        "gap": 184,
        "magType": "md",
        "type": "earthquake",
        "title": "M 1.8 - 2 km E of Magas Arriba, Puerto Rico"
      },
      "geometry": {
        "type": "Point",
        "coordinates": [
          -66.75,
          18.014,
          16.31
        ]
      },
      "id": "pr71503673"
    },
    {
      "type": "Feature",
      "properties": {
        "mag": 2.2,
        "place": "2 km NNW of Guayanilla, Puerto Rico",
        "time": 1767283753810,
        "updated": 1767284358450,
        "tz": null,
        "url": "https://earthquake.usgs.gov/earthquakes/eventpage/pr71503643",
        "detail": "https://earthquake.usgs.gov/earthquakes/feed/v1.0/detail/pr71503643.geojson",
        "felt": null,
        "cdi": null,
        "mmi": null,
        "alert": null,
        "status": "reviewed",
        "tsunami": 0,
        "sig": 74,
        "net": "pr",
        "code": "71503643",
        "ids": ",pr71503643,",
        "sources": ",pr,",
        "types": ",origin,phase-data,",
        "nst": 7,
        "dmin": 0.1027,
        "rms": 0.15,
        "gap": 147,
        "magType": "md",
        "type": "earthquake",
        "title": "M 2.2 - 2 km NNW of Guayanilla, Puerto Rico"
      },
      "geometry": {
        "type": "Point",
        "coordinates": [
          -66.7996666666667,
          18.0448333333333,
          12.13
        ]
      },
      "id": "pr71503643"
    },
    {
      "type": "Feature",
      "properties": {
        "mag": 3.99,
        "place": "27 km NNE of Miches, Dominican Republic",
        "time": 1767274534520,
        "updated": 1767281613501,
        "tz": null,
        "url": "https://earthquake.usgs.gov/earthquakes/eventpage/pr2026001000",
        "detail": "https://earthquake.usgs.gov/earthquakes/feed/v1.0/detail/pr2026001000.geojson",
        "felt": null,
        "cdi": null,
        "mmi": null,
        "alert": null,
        "status": "reviewed",
        "tsunami": 0,
        "sig": 245,
        "net": "pr",
        "code": "2026001000",
        "ids": ",us7000rlxb,pr2026001000,",
        "sources": ",us,pr,",
        "types": ",origin,phase-data,",
        "nst": 24,
        "dmin": 0.9033,
        "rms": 0.7,
        "gap": 189,
        "magType": "md",
        "type": "earthquake",
        "title": "M 4.0 - 27 km NNE of Miches, Dominican Republic"
      },
      "geometry": {
        "type": "Point",
        "coordinates": [
          -68.9508,
          19.2151,
          37
        ]
      },
      "id": "pr2026001000"
    },
    {
      "type": "Feature",
      "properties": {
        "mag": 4.6,
        "place": "28 km WSW of La Concepción, Venezuela",
        "time": 1767271024252,
        "updated": 1767294722559,
        "tz": null,
        "url": "https://earthquake.usgs.gov/earthquakes/eventpage/us7000rlwx",
        "detail": "https://earthquake.usgs.gov/earthquakes/feed/v1.0/detail/us7000rlwx.geojson",
        "felt": 1,
        "cdi": 2,
        "mmi": null,
        "alert": null,
        "status": "reviewed",
        "tsunami": 0,
        "sig": 326,
        "net": "us",
        "code": "7000rlwx",
        "ids": ",us7000rlwx,",
        "sources": ",us,",
        "types": ",dyfi,origin,phase-data,",
        "nst": 38,
        "dmin": 2.141,
        "rms": 1.31,
        "gap": 59,
        "magType": "mb",
        "type": "earthquake",
        "title": "M 4.6 - 28 km WSW of La Concepción, Venezuela"
      },
      "geometry": {
        "type": "Point",
        "coordinates": [
          -72.0685,
          10.5015,
          10
        ]
      },
      "id": "us7000rlwx"
    },
    {
      "type": "Feature",
      "properties": {
        "mag": 1.91,
        "place": "1 km ENE of Fuig, Puerto Rico",
        "time": 1767268184190,
        "updated": 1767269769370,
        "tz": null,
        "url": "https://earthquake.usgs.gov/earthquakes/eventpage/pr71503608",
        "detail": "https://earthquake.usgs.gov/earthquakes/feed/v1.0/detail/pr71503608.geojson",
        "felt": null,
        "cdi": null,
        "mmi": null,
        "alert": null,
        "status": "reviewed",
        "tsunami": 0,
        "sig": 56,
        "net": "pr",
        "code": "71503608",
        "ids": ",pr71503608,",
        "sources": ",pr,",
        "types": ",origin,phase-data,",
        "nst": 5,
        "dmin": 0.02638,
        "rms": 0.04,
        "gap": 137,
        "magType": "md",
        "type": "earthquake",
        "title": "M 1.9 - 1 km ENE of Fuig, Puerto Rico"
      },
      "geometry": {
        "type": "Point",
        "coordinates": [
          -66.9016666666667,
          17.9906666666667,
          11.49
        ]
      },
      "id": "pr71503608"
    },
    {
      "type": "Feature",
      "properties": {
        "mag": 3.42,
        "place": "81 km NNW of San Antonio, Puerto Rico",
        "time": 1767265656690,
        "updated": 1767266765200,
        "tz": null,
        "url": "https://earthquake.usgs.gov/earthquakes/eventpage/pr71503598",
        "detail": "https://earthquake.usgs.gov/earthquakes/feed/v1.0/detail/pr71503598.geojson",
        "felt": null,
        "cdi": null,
        "mmi": null,
        "alert": null,
        "status": "reviewed",
        "tsunami": 0,
        "sig": 180,
        "net": "pr",
        "code": "71503598",
        "ids": ",pr71503598,",
        "sources": ",pr,",
        "types": ",origin,phase-data,",
        "nst": 17,
        "dmin": 0.7534,
        "rms": 0.23,
        "gap": 233,
        "magType": "md",
        "type": "earthquake",
        "title": "M 3.4 - 81 km NNW of San Antonio, Puerto Rico"
      },
      "geometry": {
        "type": "Point",
        "coordinates": [
          -67.3828333333333,
          19.1793333333333,
          23.81
        ]
      },
      "id": "pr71503598"
    },
    {
      "type": "Feature",
      "properties": {
        "mag": 2.87,
        "place": "2 km SSE of Magas Arriba, Puerto Rico",
        "time": 1767261769580,
        "updated": 1767263561770,
        "tz": null,
        "url": "https://earthquake.usgs.gov/earthquakes/eventpage/pr71503568",
        "detail": "https://earthquake.usgs.gov/earthquakes/feed/v1.0/detail/pr71503568.geojson",
        "felt": null,
        "cdi": null,
        "mmi": null,
        "alert": null,
        "status": "reviewed",
        "tsunami": 0,
        "sig": 127,
        "net": "pr",
        "code": "71503568",
        "ids": ",pr71503568,",
        "sources": ",pr,",
        "types": ",origin,phase-data,",
        "nst": 17,
        "dmin": 0.113,
        "rms": 0.25,
        "gap": 142,
        "magType": "md",
        "type": "earthquake",
        "title": "M 2.9 - 2 km SSE of Magas Arriba, Puerto Rico"
      },
      "geometry": {
        "type": "Point",
        "coordinates": [
          -66.7635,
          18.0001666666667,
          13.28
        ]
      },
      "id": "pr71503568"
    },
    {
      "type": "Feature",
      "properties": {
        "mag": 3.41,
        "place": "103 km NNW of San Antonio, Puerto Rico",
        "time": 1767256292890,
        "updated": 1767258821860,
        "tz": null,
        "url": "https://earthquake.usgs.gov/earthquakes/eventpage/pr71503548",
        "detail": "https://earthquake.usgs.gov/earthquakes/feed/v1.0/detail/pr71503548.geojson",
        "felt": null,
        "cdi": null,
        "mmi": null,
        "alert": null,
        "status": "reviewed",
        "tsunami": 0,
        "sig": 179,
        "net": "pr",
        "code": "71503548",
        "ids": ",us7000rlv5,pr71503548,",
        "sources": ",us,pr,",
        "types": ",origin,phase-data,",
        "nst": 21,
        "dmin": 0.9539,
        "rms": 0.47,
        "gap": 200,
        "magType": "md",
        "type": "earthquake",
        "title": "M 3.4 - 103 km NNW of San Antonio, Puerto Rico"
      },
      "geometry": {
        "type": "Point",
        "coordinates": [
          -67.3883333333333,
          19.3895,
          54.54
        ]
      },
      "id": "pr71503548"
    },
    {
      "type": "Feature",
      "properties": {
        "mag": 2.48,
        "place": "4 km SSE of Indios, Puerto Rico",
        "time": 1767246147790,
        "updated": 1767247150640,
        "tz": null,
        "url": "https://earthquake.usgs.gov/earthquakes/eventpage/pr71503528",
        "detail": "https://earthquake.usgs.gov/earthquakes/feed/v1.0/detail/pr71503528.geojson",
        "felt": null,
        "cdi": null,
        "mmi": null,
        "alert": null,
        "status": "reviewed",
        "tsunami": 0,
        "sig": 95,
        "net": "pr",
        "code": "71503528",
        "ids": ",pr71503528,",
        "sources": ",pr,",
        "types": ",origin,phase-data,",
        "nst": 11,
        "dmin": 0.07951,
        "rms": 0.41,
        "gap": 168,
        "magType": "md",
        "type": "earthquake",
        "title": "M 2.5 - 4 km SSE of Indios, Puerto Rico"
      },
      "geometry": {
        "type": "Point",
        "coordinates": [
          -66.7975,
          17.9586666666667,
          10.48
        ]
      },
      "id": "pr71503528"
    },
    {
      "type": "Feature",
      "properties": {
        "mag": 2.46,
        "place": "2 km NNW of Las Marias, Puerto Rico",
        "time": 1767236897930,
        "updated": 1767238287330,
        "tz": null,
        "url": "https://earthquake.usgs.gov/earthquakes/eventpage/pr71503513",
        "detail": "https://earthquake.usgs.gov/earthquakes/feed/v1.0/detail/pr71503513.geojson",
        "felt": null,
        "cdi": null,
        "mmi": null,
        "alert": null,
        "status": "reviewed",
        "tsunami": 0,
        "sig": 93,
        "net": "pr",
        "code": "71503513",
        "ids": ",pr71503513,",
        "sources": ",pr,",
        "types": ",origin,phase-data,",
        "nst": 11,
        "dmin": 0.08976,
        "rms": 0.18,
        "gap": 113,
        "magType": "md",
        "type": "earthquake",
        "title": "M 2.5 - 2 km NNW of Las Marias, Puerto Rico"
      },
      "geometry": {
        "type": "Point",
        "coordinates": [
          -67.158,
          18.3168333333333,
          24.82
        ]
      },
      "id": "pr71503513"
    },
    {
      "type": "Feature",
      "properties": {
        "mag": 2.29,
        "place": "4 km S of Indios, Puerto Rico",
        "time": 1767232159980,
        "updated": 1767233362280,
        "tz": null,
        "url": "https://earthquake.usgs.gov/earthquakes/eventpage/pr71503508",
        "detail": "https://earthquake.usgs.gov/earthquakes/feed/v1.0/detail/pr71503508.geojson",
        "felt": null,
        "cdi": null,
        "mmi": null,
        "alert": null,
        "status": "reviewed",
        "tsunami": 0,
        "sig": 81,
        "net": "pr",
        "code": "71503508",
        "ids": ",pr71503508,",
        "sources": ",pr,",
        "types": ",origin,phase-data,",
        "nst": 7,
        "dmin": 0.05744,
        "rms": 0.13,
        "gap": 212,
        "magType": "md",
        "type": "earthquake",
        "title": "M 2.3 - 4 km S of Indios, Puerto Rico"
      },
      "geometry": {
        "type": "Point",
        "coordinates": [
          -66.8226666666667,
          17.955,
          11.33
        ]
      },
      "id": "pr71503508"
    }
  ],
  "bbox": [
    -176.18133333333,
    -45.6205,
    -0.94999998807907,
    178.5343,
    64.999,
    190.212
  ]
}
